haemwend/__init__.py
haemwend/main.py
haemwend-0.0.1.dist-info/WHEEL
haemwend-0.0.1.dist-info/entry_points.txt
haemwend-0.0.1.dist-info/METADATA
haemwend-0.0.1.dist-info/RECORD
