Metadata-Version: 2.3
Name: haemwend
Version: 0.0.1
Summary: A Fantasy MMO Experience
Author: NostraDavid
Author-email: NostraDavid <55331731+NostraDavid@users.noreply.github.com>
Requires-Python: >=3.13
